[{"source": "readme", "content": [{"Setting": "api_url", "Required": false, "Default": "None", "Description": "Optionally overrides the default base URL for the Gitlab API. If no path is provided, the base URL will be appended with /api/v4. E.g. 'https://gitlab.com' becomes 'https://gitlab.com/api/v4'."}, {"Setting": "graphql_api_url_base", "Required": false, "Default": "None", "Description": "Optionally overrides the default base URL for the Gitlab Graphql API. Example. 'https://gitlab.com/api'."}, {"Setting": "private_token", "Required": true, "Default": "None", "Description": "An access token to use when calling to the Gitlab API."}, {"Setting": "groups", "Required": false, "Default": "None", "Description": "A space delimited list of group ids, e.g. 'orgname1 orgname2 orgname3'"}, {"Setting": "projects", "Required": false, "Default": "None", "Description": "A space delimited list of project ids, e.g. 'orgname/projectname1 orgname/projectname2"}, {"Setting": "start_date", "Required": false, "Default": "None", "Description": "Optional. If provided, this is the furthest date for which data will be retrieved."}, {"Setting": "ultimate_license", "Required": false, "Default": "False", "Description": "If not set to 'true', the following streams will be ignored: 'epics' and 'epic_issues'."}, {"Setting": "fetch_merge_request_commits", "Required": false, "Default": "False", "Description": "If not set to 'true', the 'merge_request_commits' stream will be ignored."}, {"Setting": "fetch_pipelines_extended", "Required": false, "Default": "False", "Description": "If not set to 'true', the 'pipelines_extended' stream will be ignored."}, {"Setting": "fetch_group_variables", "Required": false, "Default": "False", "Description": "If not set to 'true', the 'group_variables' stream will be ignored."}, {"Setting": "fetch_project_variables", "Required": false, "Default": "False", "Description": "If not set to 'true', the 'project_variables' stream will be ignored."}, {"Setting": "fetch_site_users", "Required": false, "Default": "None", "Description": "Unless set to 'false', the 'site_users' stream will be included."}, {"Setting": "requests_cache_path", "Required": false, "Default": "None", "Description": "(Optional.) Specifies the directory of API request caches.When this is set, the cache will be used before calling to the external API endpoint. Any data not already cached will be recorded to this path as it is received."}, {"Setting": "stream_maps", "Required": false, "Default": "None", "Description": "Config object for stream maps capability."}, {"Setting": "stream_map_config", "Required": false, "Default": "None", "Description": "User-defined config values to be used within map expressions."}, {"Setting": "flattening_enabled", "Required": false, "Default": "None", "Description": "'True' to enable schema flattening and automatically expand nested properties."}, {"Setting": "flattening_max_depth", "Required": false, "Default": "None", "Description": "The max depth to flatten schemas."}], "instance": 0}]