{"url": "https://github.com/meltanolabs/tap-airbyte-wrapper", "api_url": "https://api.github.com/repos/meltanolabs/tap-airbyte-wrapper", "account": "meltanolabs", "repo_name": "tap-airbyte-wrapper", "account_type": "organization", "language": "Python", "readme": {"is_present": true, "url": "https://raw.githubusercontent.com/meltanolabs/tap-airbyte-wrapper/master/README.md"}, "sample_config": {"is_present": false, "url": null}, "stats": {"num_stars": 20, "num_watchers": 20, "num_forks": 2, "num_networks": 2, "num_subscribers": 1, "num_open_issues": 3, "num_open_issues_30D": 2, "num_closed_issues": 4, "num_closed_issues_30D": 0, "num_open_pr": 1, "num_open_pr_30D": 1, "num_closed_pr": 0, "num_closed_pr_30D": 0}, "timestamps": {"ts_created_at": ["2022-12-12T09:59:04Z"], "ts_last_updated_at": "2024-02-20T23:39:19Z", "ts_last_pushed_at": "2024-02-16T20:03:50Z", "ts_last_open_issue_at": "2024-02-16T20:03:49Z", "ts_last_closed_issue_at": "2022-12-23T01:16:05Z", "ts_last_open_pr_at": "2024-02-16T20:03:49Z", "ts_last_closed_pr_at": null}}