[{"source": "readme", "content": [{"Setting": "sqlalchemy_url", "Required": false, "Default": "None", "Description": "SQLAlchemy connection string"}, {"Setting": "table_name", "Required": false, "Default": "None", "Description": "The name of the table to write to."}, {"Setting": "default_target_schema", "Required": false, "Default": "None", "Description": "The default target database schema name to use for all streams."}, {"Setting": "stream_maps", "Required": false, "Default": "None", "Description": "Config object for stream maps capability. For more information check out Stream Maps."}, {"Setting": "stream_map_config", "Required": false, "Default": "None", "Description": "User-defined config values to be used within map expressions."}, {"Setting": "flattening_enabled", "Required": false, "Default": "None", "Description": "'True' to enable schema flattening and automatically expand nested properties."}, {"Setting": "flattening_max_depth", "Required": false, "Default": "None", "Description": "The max depth to flatten schemas."}], "instance": 0}]