{"url": "https://github.com/sehnem/tap-netsuite", "api_url": "https://api.github.com/repos/sehnem/tap-netsuite", "account": "sehnem", "repo_name": "tap-netsuite", "account_type": "user", "language": "Python", "readme": {"is_present": true, "url": "https://raw.githubusercontent.com/sehnem/tap-netsuite/master/README.md"}, "sample_config": {"is_present": false, "url": null}, "stats": {"num_stars": 2, "num_watchers": 2, "num_forks": 1, "num_networks": 1, "num_subscribers": 1, "num_open_issues": 0, "num_open_issues_30D": 0, "num_closed_issues": 5, "num_closed_issues_30D": 2, "num_open_pr": 0, "num_open_pr_30D": 0, "num_closed_pr": 5, "num_closed_pr_30D": 2}, "timestamps": {"ts_created_at": ["2023-04-21T19:53:02Z"], "ts_last_updated_at": "2023-08-10T21:05:19Z", "ts_last_pushed_at": "2023-08-01T16:48:39Z", "ts_last_open_issue_at": null, "ts_last_closed_issue_at": "2023-08-01T16:48:39Z", "ts_last_open_pr_at": null, "ts_last_closed_pr_at": "2023-08-01T16:48:39Z"}}